{
  "name": "Centeda",
  "url": "centeda.com",
  "version": "0.1.4",
  "parent": "verecor.com",
  "addedDatetime": 1677736800000,
  "steps": [
    {
      "stepType": "scan",
      "scanType": "templatedUrl",
      "actions": [
        {
          "actionType": "navigate",
          "id": "2f6639c0-201f-4d5e-8467-ae0ba457b409",
          "url": "https://centeda.com/profile/search?fname=${firstName}&lname=${lastName}&state=${state}&city=${city}&fage=${age|ageRange}",
          "ageRange": [
            "18-30",
            "31-40",
            "41-50",
            "51-60",
            "61-70",
            "71-80",
            "81+"
          ]
        },
        {
          "actionType": "extract",
          "id": "e2e236b0-515b-43b3-9154-0432ed9b7566",
          "selector": ".search-item",
          "profile": {
            "name": {
              "selector": ".title",
              "beforeText": "Age "
            },
            "alternativeNamesList": {
              "selector": ".//div[@class='col-sm-24 col-md-8 known-as']//li",
              "findElements": true
            },
            "age": {
              "selector": ".age"
            },
            "addressCityStateList": {
              "selector": ".//div[@class='col-sm-24 col-md-8 lived-in']//li",
              "findElements": true
            },
            "relativesList": {
              "selector": ".//div[@class='col-sm-24 col-md-8 related-to']//li"
            },
            "profileUrl": {
              "selector": ".get-report-btn"
            }
          }
        }
      ]
    },
    {
      "stepType": "optOut",
      "optOutType": "parentSiteOptOut",
      "actions": []
    }
  ],
  "schedulingConfig": {
    "retryError": 48,
    "confirmOptOutScan": 72,
    "maintenanceScan": 240
  }
}